Taskmaster/__init__.py
Taskmaster/email_utils.py
Taskmaster/excel_utils.py
Taskmaster/sql_utils.py
BCHS_PopHealth-0.1.0.dist-info/LICENSE
BCHS_PopHealth-0.1.0.dist-info/METADATA
BCHS_PopHealth-0.1.0.dist-info/WHEEL
BCHS_PopHealth-0.1.0.dist-info/top_level.txt
BCHS_PopHealth-0.1.0.dist-info/RECORD
